singular_server_management/__init__.py
singular_server_management/file_templates/gunicorn_default.service
singular_server_management/file_templates/gunicorn_default.socket
singular_server_management/file_templates/nginx_file
singular_server_management/file_templates/riocoletas
singular_server_management/management/__init__.py
singular_server_management/management/commands/__init__.py
singular_server_management/management/commands/build_project.py
singular_server_management/management/commands/server_base_command.py
singular_server_management/management/commands/update_project.py
singular_server_management/routes/__init__.py
singular_server_management/routes/routes.py
singular_server_management/tests/__init__.py
singular_server_management/tests/tests.py
singular_server_management/webhooks/__init__.py
singular_server_management/webhooks/webhooks.py
singular_server_management-0.0.12.dist-info/METADATA
singular_server_management-0.0.12.dist-info/WHEEL
singular_server_management-0.0.12.dist-info/top_level.txt
singular_server_management-0.0.12.dist-info/RECORD
