Metadata-Version: 2.1
Name: singular-server-management
Version: 0.0.12
Summary: Server management
Home-page: https://lucas@bitbucket.org/singular-dev/singular_server_management.git
Author: Singular Sistemas
Author-email: ivan@singular.inf.br
License: UNKNOWN
Platform: UNKNOWN
Requires-Python: >=3.6
Requires-Dist: django
Requires-Dist: fabric
Requires-Dist: invoke
Requires-Dist: django-crontab
